temp4hifu/__init__.py
temp4hifu/calculateBioheat.py
temp4hifu/calculateRayleighIntegral.py
temp4hifu/setParam.py
temp4hifu/startApp.py
temp4hifu-1.0.0.dist-info/LICENSE
temp4hifu-1.0.0.dist-info/METADATA
temp4hifu-1.0.0.dist-info/WHEEL
temp4hifu-1.0.0.dist-info/top_level.txt
temp4hifu-1.0.0.dist-info/RECORD
