Metadata-Version: 2.1
Name: temp4hifu
Version: 1.0.0
Summary: A Python package designed to estimate the temperature increase due to high intensity focused ultrasound (HIFU) excitation
Home-page: https://github.com/C2H5OH-Consumer/temp4hifu
Author: Gerald Lee
Author-email: Gerald Lee <gerald13@uw.edu>
License: MIT
Project-URL: Homepage, https://github.com/C2H5OH-Consumer/temp4hifu
Classifier: Programming Language :: Python :: 3
Classifier: License :: OSI Approved :: MIT License
Classifier: Operating System :: OS Independent
Requires-Python: >=3.8
License-File: LICENSE
